Metadata-Version: 2.1
Name: betaincder
Version: 0.1.1
Summary: compute the incomplete Beta function and its derivatives
Home-page: UNKNOWN
Author: Caner Turkmen
Author-email: caner.turkmen@boun.edu.tr
License: MIT
Platform: UNKNOWN
Classifier: Programming Language :: Python :: 2.7
Classifier: Programming Language :: Python :: 3.6
Classifier: Programming Language :: Cython
Classifier: Development Status :: 2 - Pre-Alpha
Classifier: Intended Audience :: Developers
Classifier: Intended Audience :: Science/Research
Classifier: License :: OSI Approved :: MIT License
Classifier: Topic :: Scientific/Engineering
Classifier: Topic :: Scientific/Engineering :: Information Analysis
Classifier: Topic :: Scientific/Engineering :: Mathematics
